COPYING
LICENSE
MANIFEST.in
README.rst
forbidden_email_providers.txt
requirements-dev.txt
requirements-ext.txt
requirements.txt
setup.cfg
setup.py
tox.ini
doc/Makefile
doc/make.bat
doc/build/doctrees/api.doctree
doc/build/doctrees/configure.doctree
doc/build/doctrees/environment.pickle
doc/build/doctrees/features.doctree
doc/build/doctrees/index.doctree
doc/build/doctrees/install.doctree
doc/build/doctrees/python.doctree
doc/build/doctrees/reference.doctree
doc/build/doctrees/usage.doctree
doc/build/html/.buildinfo
doc/build/html/api.html
doc/build/html/configure.html
doc/build/html/features.html
doc/build/html/genindex.html
doc/build/html/http-routingtable.html
doc/build/html/index.html
doc/build/html/install.html
doc/build/html/objects.inv
doc/build/html/py-modindex.html
doc/build/html/python.html
doc/build/html/reference.html
doc/build/html/search.html
doc/build/html/searchindex.js
doc/build/html/usage.html
doc/build/html/_sources/api.txt
doc/build/html/_sources/configure.txt
doc/build/html/_sources/features.txt
doc/build/html/_sources/index.txt
doc/build/html/_sources/install.txt
doc/build/html/_sources/python.txt
doc/build/html/_sources/reference.txt
doc/build/html/_sources/usage.txt
doc/build/html/_static/ajax-loader.gif
doc/build/html/_static/basic.css
doc/build/html/_static/comment-bright.png
doc/build/html/_static/comment-close.png
doc/build/html/_static/comment.png
doc/build/html/_static/doctools.js
doc/build/html/_static/down-pressed.png
doc/build/html/_static/down.png
doc/build/html/_static/file.png
doc/build/html/_static/jquery-1.11.1.js
doc/build/html/_static/jquery.js
doc/build/html/_static/minus.png
doc/build/html/_static/plus.png
doc/build/html/_static/pygments.css
doc/build/html/_static/searchtools.js
doc/build/html/_static/underscore-1.3.1.js
doc/build/html/_static/underscore.js
doc/build/html/_static/up-pressed.png
doc/build/html/_static/up.png
doc/build/html/_static/websupport.js
doc/build/html/_static/css/badge_only.css
zds_member.egg-info/PKG-INFO
zds_member.egg-info/SOURCES.txt
zds_member.egg-info/dependency_links.txt
zds_member.egg-info/requires.txt
zds_member.egg-info/top_level.txt